{"sourceId":"sudoku/rpd3h3nrp2","stableKey":"sudoku_rpd3h3nrp2","cacheKey":"sudoku_rpd3h3nrp2","sudokuPadUrl":"https://app.crackingthecryptic.com/sudoku/rpd3h3nrp2","fetchedAt":"2026-03-12T18:44:00.113Z","payload":"{id:'rpd3h3nrp2',cs:50,ce:[[,,,,,,,,],[,,,,,,,,{v:3}],[,,{v:4},,,,,,],[,,,,,,,{v:3},],[,,,,,,,,],[,{v:3},,,,,,,],[,,,,,,{v:4},,],[{v:3},,,,,,,,],[,,,,,,,,]],re:[[[0,0],[0,1],[0,2],[1,0],[1,1],[1,2],[2,0],[2,1],[2,2]],[[3,0],[3,1],[3,2],[4,0],[4,1],[4,2],[5,0],[5,1],[5,2]],[[6,0],[6,1],[6,2],[7,0],[7,1],[7,2],[8,0],[8,1],[8,2]],[[0,3],[0,4],[0,5],[1,3],[1,4],[1,5],[2,3],[2,4],[2,5]],[[3,3],[3,4],[3,5],[4,3],[4,4],[4,5],[5,3],[5,4],[5,5]],[[6,3],[6,4],[6,5],[7,3],[7,4],[7,5],[8,3],[8,4],[8,5]],[[0,6],[0,7],[0,8],[1,6],[1,7],[1,8],[2,6],[2,7],[2,8]],[[3,6],[3,7],[3,8],[4,6],[4,7],[4,8],[5,6],[5,7],[5,8]],[[6,6],[6,7],[6,8],[7,6],[7,7],[7,8],[8,6],[8,7],[8,8]]],ca:[{v:'title: Octopus'},{v:'author: Aad van de Wetering'},{v:'rules: Normal sudoku rules apply, and identical digits cannot be within a king\\'s move (touching each other diagonally). Digits along arrows sum to the numbers in the circles/pills - 2-digit numbers read left-to-right or downwards.'}],a:[{wp:[[4.5,1.8],[4.5,4.4]],c:CFCFCF,th:5,hl:0.3},{wp:[[4.5,7.2],[4.5,4.6]],c:CFCFCF,th:5,hl:0.3},{wp:[[1.8,4.5],[4.4,4.5]],c:CFCFCF,th:5,hl:0.3},{wp:[[7.2,4.5],[4.6,4.5]],c:CFCFCF,th:5,hl:0.3},{wp:[[7.2,7.2],[5.5,5.5]],c:CFCFCF,th:5,hl:0.3},{wp:[[7.2,1.8],[5.5,3.5]],c:CFCFCF,th:5,hl:0.3},{wp:[[1.8,1.8],[3.5,3.5]],c:CFCFCF,th:5,hl:0.3},{wp:[[1.8,7.2],[3.5,5.5]],c:CFCFCF,th:5,hl:0.3}],o:[{ct:[1.5,1.5],w:0.85,h:0.85,c1:CFCFCF,c2:#F,r:t,fs:12,te:''},{ct:[1.5,7.5],w:0.85,h:0.85,c1:CFCFCF,c2:#F,r:t,fs:12,te:''},{ct:[7.5,7.5],w:0.85,h:0.85,c1:CFCFCF,c2:#F,r:t,fs:12,te:''},{ct:[7.5,1.5],w:0.85,h:0.85,c1:CFCFCF,c2:#F,r:t,fs:12,te:''},{ct:[4.5,1],w:1.85,h:0.85,c1:CFCFCF,c2:#F,r:t,fs:12,te:''},{ct:[4.5,8],w:1.85,h:0.85,c1:CFCFCF,c2:#F,r:t,fs:12,te:''},{ct:[1,4.5],w:0.85,h:1.85,c1:CFCFCF,c2:#F,r:t,fs:12,te:''},{ct:[8,4.5],w:0.85,h:1.85,c1:CFCFCF,c2:#F,r:t,fs:12,te:''}],vd:[{id:'npAyDz4ypUM',publishedAt:'2021-04-13T22:00:13Z',t:'Wrestling the Octopus',d:1273}]}"}