{"sourceId":"sudoku/782JMppRnf","stableKey":"sudoku_782JMppRnf","cacheKey":"sudoku_782JMppRnf","sudokuPadUrl":"https://app.crackingthecryptic.com/sudoku/782JMppRnf","fetchedAt":"2026-03-17T00:40:05.575Z","payload":"{id:'782JMppRnf',cs:50,ce:[[,,,,,,,,],[,,,,,,,,],[,,,,,,,,],[,,,,,,,,],[,,,,,,,,],[,,,,,,,,],[,,,,,,,,],[,,,,,,,,],[,,,,,,,,]],re:[[[0,0],[0,1],[0,2],[1,0],[1,1],[1,2],[2,0],[2,1],[2,2]],[[3,0],[3,1],[3,2],[4,0],[4,1],[4,2],[5,0],[5,1],[5,2]],[[6,0],[6,1],[6,2],[7,0],[7,1],[7,2],[8,0],[8,1],[8,2]],[[0,3],[0,4],[0,5],[1,3],[1,4],[1,5],[2,3],[2,4],[2,5]],[[3,3],[3,4],[3,5],[4,3],[4,4],[4,5],[5,3],[5,4],[5,5]],[[6,3],[6,4],[6,5],[7,3],[7,4],[7,5],[8,3],[8,4],[8,5]],[[0,6],[0,7],[0,8],[1,6],[1,7],[1,8],[2,6],[2,7],[2,8]],[[3,6],[3,7],[3,8],[4,6],[4,7],[4,8],[5,6],[5,7],[5,8]],[[6,6],[6,7],[6,8],[7,6],[7,7],[7,8],[8,6],[8,7],[8,8]]],ca:[{ce:[[0,4],[1,4],[2,4],[3,4]],v:19},{ce:[[1,6],[0,6],[0,7]],v:16},{ce:[[2,6],[2,7],[1,7],[1,8],[2,8]],v:18},{ce:[[4,6],[5,6],[5,7],[4,7]],v:19},{ce:[[5,8],[6,8],[7,8],[7,7]],v:14},{ce:[[6,4],[7,4],[7,5]],v:15},{ce:[[5,0],[6,0],[6,1],[5,1]],v:26},{v:'title: Look, Don\\'t Kill'},{v:'author: Derektionary'},{v:'rules: Normal sudoku rules apply. Along thermometers, digits must increase from the bulb end. Digits along arrows must sum to the digit in that arrow\\'s circle. The cages in the grid are either killer cages or look-and-say cages (or both). It is up to the solver to determine which cage is which. In a killer cage, digits cannot repeat and must sum to the small clue in the top left corner of the cage. In a Look-and-Say cage, digits CAN repeat and the small clue in the top left corner should be read as a look-and-say number (ie it says which digits are in that cage). For example, if a look-and-say cage has the clue \\'12\\' then it means there is one 2 in the cage. If it has the clue \\'33\\' then it means there are three 3s in the cage.'}],l:[{wp:[[0.5,4.5],[3.5,4.5]],c:CFCFCF,th:10},{wp:[[4.5,5.5],[4.5,7.5]],c:CFCFCF,th:10},{wp:[[8.5,3.5],[8.5,4.5],[7.5,4.5]],c:CFCFCF,th:10},{wp:[[8.5,6.5],[7.5,6.5]],c:CFCFCF,th:10},{wp:[[6.5,0.5],[6.5,2.5]],c:CFCFCF,th:10}],a:[{wp:[[3.2,8.5],[2.5,8.5],[2.5,6.5],[3.5,6.5]],c:CFCFCF,th:2,hl:0.3},{wp:[[0.5,7.2],[0.5,6.5],[1.5,6.5],[1.5,5.5]],c:CFCFCF,th:2,hl:0.3},{wp:[[2.2,3.5],[1.5,3.5],[1.5,2.5],[3.5,2.5]],c:CFCFCF,th:2,hl:0.3},{wp:[[5.5,6.2],[5.5,3.5]],c:CFCFCF,th:2,hl:0.3},{wp:[[7.5,3.2],[7.5,0.5]],c:CFCFCF,th:2,hl:0.3},{c:CFCFCF,th:2,hl:0.3}],u:[{ct:[0.5,4.5],w:0.7,h:0.7,c1:CFCFCF,c2:CFCFCF,r:t},{ct:[4.5,5.5],w:0.7,h:0.7,c1:CFCFCF,c2:CFCFCF,r:t},{ct:[8.5,3.5],w:0.7,h:0.7,c1:CFCFCF,c2:CFCFCF,r:t},{ct:[8.5,6.5],w:0.7,h:0.7,c1:CFCFCF,c2:CFCFCF,r:t},{ct:[6.5,0.5],w:0.7,h:0.7,c1:CFCFCF,c2:CFCFCF,r:t},{ct:[0.5,7.5],w:0.7,h:0.7,c1:CFCFCF,c2:#F,r:t},{ct:[3.5,8.5],w:0.7,h:0.7,c1:CFCFCF,c2:#F,r:t},{ct:[2.5,3.5],w:0.7,h:0.7,c1:CFCFCF,c2:#F,r:t},{ct:[5.5,6.5],w:0.7,h:0.7,c1:CFCFCF,c2:#F,r:t},{ct:[7.5,3.5],w:0.7,h:0.7,c1:CFCFCF,c2:#F,r:t}],vd:[{id:'I7atuVv5DAQ',publishedAt:'2022-08-07T19:30:01Z',t:'How To Confuse A YouTuber!',d:2992}]}"}