{"sourceId":"sudoku/PnBnQfpPfR","stableKey":"sudoku_PnBnQfpPfR","cacheKey":"sudoku_PnBnQfpPfR","sudokuPadUrl":"https://app.crackingthecryptic.com/sudoku/PnBnQfpPfR","fetchedAt":"2026-03-12T18:43:51.585Z","payload":"{id:'PnBnQfpPfR',cs:50,ce:[[,,,,,],[,,,,,],[,,,,,],[,,,,,],[,,,,,],[,,,,,]],re:[[[0,0],[0,1],[0,2],[1,0],[1,1],[1,2]],[[0,3],[0,4],[0,5],[1,3],[1,4],[1,5]],[[2,0],[2,1],[2,2],[3,0],[3,1],[3,2]],[[2,3],[2,4],[2,5],[3,3],[3,4],[3,5]],[[4,0],[4,1],[4,2],[5,0],[5,1],[5,2]],[[4,3],[4,4],[4,5],[5,3],[5,4],[5,5]]],ca:[{v:'title: 6/10'},{v:'author: HawkAvatar'},{v:'rules: This puzzle uses six of the digits 0-9; the solver must determine which six. Place one copy of each digit in each row/column/box. Digits along thermometers increase from the bulb end. Digits along an arrow sum to the digit in that arrow\\'s circle. Cells separated by a V contain digits summing to 5; ALL possible Vs are given.'}],l:[{wp:[[5.5,0.5],[2.5,0.5]],c:CFCFCF,th:10},{wp:[[4.5,5.5],[3.5,5.5]],c:CFCFCF,th:10},{c:CFCFCF,th:10}],a:[{wp:[[0.5,5.2],[0.5,4.5],[1.5,4.5],[1.5,2.5]],c:CFCFCF,th:2,hl:0.3},{wp:[[5.2,1.5],[2.5,1.5],[2.5,2.5]],c:CFCFCF,th:2,hl:0.3},{wp:[[2.5,3.8],[2.5,5.5]],c:CFCFCF,th:2,hl:0.3},{c:CFCFCF,th:2,hl:0.3}],u:[{ct:[5.5,0.5],w:0.7,h:0.7,c1:CFCFCF,c2:CFCFCF,r:t},{ct:[4.5,5.5],w:0.7,h:0.7,c1:CFCFCF,c2:CFCFCF,r:t},{ct:[0.5,5.5],w:0.7,h:0.7,c1:CFCFCF,c2:#F,r:t},{ct:[2.5,3.5],w:0.7,h:0.7,c1:CFCFCF,c2:#F,r:t},{ct:[5.5,1.5],w:0.7,h:0.7,c1:CFCFCF,c2:#F,r:t}],o:[{ct:[5,0.5],w:0.25,h:0.25,r:f,fs:20,te:'V'},{ct:[3.5,2],w:0.25,h:0.25,r:f,fs:20,te:'V'},{ct:[1.5,3],w:0.25,h:0.25,r:f,fs:20,te:'V'},{ct:[1,3.5],w:0.25,h:0.25,r:f,fs:20,te:'V'},{ct:[1.5,5],w:0.25,h:0.25,r:f,fs:20,te:'V'},{ct:[2.5,5],w:0.25,h:0.25,r:f,fs:20,te:'V'},{ct:[3,3.5],w:0.25,h:0.25,r:f,fs:20,te:'V'}],vd:[{id:'Zj03VieODwQ',publishedAt:'2023-02-18T00:04:40Z',t:'Normal Sudoku SIZE Does Not Apply',d:1098}]}"}